{
	"info": {
		"_postman_id": "0cd799c3-63a3-4922-9000-717f3b097f96",
		"name": "nomination",
		"schema": "https://schema.getpostman.com/json/collection/v2.1.0/collection.json",
		"_exporter_id": "25809818"
	},
	"item": [
		{
			"name": "Returns a list of nominations sorted by date received from the President.",
			"request": {
				"method": "GET",
				"header": [],
				"url": {
					"raw": "https://api.congress.gov/v3/nomination",
					"protocol": "https",
					"host": [
						"api",
						"congress",
						"gov"
					],
					"path": [
						"v3",
						"nomination"
					]
				}
			},
			"response": []
		},
		{
			"name": "Returns a list of nominations filtered by the specified congress and sorted by date received from the President.",
			"request": {
				"method": "GET",
				"header": [],
				"url": {
					"raw": "https://api.congress.gov/v3/nomination/117",
					"protocol": "https",
					"host": [
						"api",
						"congress",
						"gov"
					],
					"path": [
						"v3",
						"nomination",
						"117"
					]
				}
			},
			"response": []
		},
		{
			"name": "Returns detailed information for a specified nomination.",
			"request": {
				"method": "GET",
				"header": [],
				"url": {
					"raw": "https://api.congress.gov/v3/nomination/117/2467",
					"protocol": "https",
					"host": [
						"api",
						"congress",
						"gov"
					],
					"path": [
						"v3",
						"nomination",
						"117",
						"2467"
					]
				}
			},
			"response": []
		},
		{
			"name": "Returns the list nominees for a position within the nomination",
			"request": {
				"method": "GET",
				"header": [],
				"url": {
					"raw": "https://api.congress.gov/v3/nomination/117/2467/1",
					"protocol": "https",
					"host": [
						"api",
						"congress",
						"gov"
					],
					"path": [
						"v3",
						"nomination",
						"117",
						"2467",
						"1"
					]
				}
			},
			"response": []
		},
		{
			"name": "Returns the list of actions on a specified nomination",
			"request": {
				"method": "GET",
				"header": [],
				"url": {
					"raw": "https://api.congress.gov/v3/nomination/117/2467/actions",
					"protocol": "https",
					"host": [
						"api",
						"congress",
						"gov"
					],
					"path": [
						"v3",
						"nomination",
						"117",
						"2467",
						"actions"
					]
				}
			},
			"response": []
		},
		{
			"name": "Returns the list of committees associated with a specified nomination",
			"request": {
				"method": "GET",
				"header": [],
				"url": {
					"raw": "https://api.congress.gov/v3/nomination/117/2467/committees",
					"protocol": "https",
					"host": [
						"api",
						"congress",
						"gov"
					],
					"path": [
						"v3",
						"nomination",
						"117",
						"2467",
						"committees"
					]
				}
			},
			"response": []
		},
		{
			"name": "Returns the list of printed hearings associated with a specified nomination",
			"request": {
				"method": "GET",
				"header": [],
				"url": {
					"raw": "https://api.congress.gov/v3/nomination/116/389/hearings",
					"protocol": "https",
					"host": [
						"api",
						"congress",
						"gov"
					],
					"path": [
						"v3",
						"nomination",
						"116",
						"389",
						"hearings"
					]
				}
			},
			"response": []
		}
	],
	"auth": {
		"type": "apikey",
		"apikey": [
			{
				"key": "in",
				"value": "query",
				"type": "string"
			},
			{
				"key": "key",
				"value": "api_key",
				"type": "string"
			},
			{
				"key": "value",
				"value": "XgSmUR8FSZ7xKqxSXKC99YbWvRXAtElXSjDAH5lz",
				"type": "string"
			}
		]
	},
	"event": [
		{
			"listen": "prerequest",
			"script": {
				"type": "text/javascript",
				"packages": {},
				"exec": [
					""
				]
			}
		},
		{
			"listen": "test",
			"script": {
				"type": "text/javascript",
				"packages": {},
				"exec": [
					""
				]
			}
		}
	]
}